LICENSE
MANIFEST.in
README.rst
VERSION
setup.py
rh_util/__init__.py
rh_util/apps.py
rh_util.egg-info/PKG-INFO
rh_util.egg-info/SOURCES.txt
rh_util.egg-info/dependency_links.txt
rh_util.egg-info/top_level.txt
rh_util/cpf/__init__.py
rh_util/cpf/services.py
rh_util/crypto/__init__.py
rh_util/crypto/services.py
rh_util/date/__init__.py
rh_util/date/services.py
rh_util/django/__init__.py
rh_util/django/services.py
rh_util/error/__init__.py
rh_util/error/services.py
rh_util/files/__init__.py
rh_util/files/services.py
rh_util/impressao/__init__.py
rh_util/impressao/services.py
rh_util/json/__init__.py
rh_util/json/services.py
rh_util/marshmallow/__init__.py
rh_util/marshmallow/services.py
rh_util/sqlalchemy/__init__.py
rh_util/sqlalchemy/services.py
rh_util/upload_file_server/__init__.py
rh_util/upload_file_server/services.py